{"widgetLabel":"ตารางฟีเจอร์","header":"{title} (ฟีเจอร์: {count}, ที่เลือก: {selected})","untitled":"ไม่มีชื่อ","relatedRecords":"บันทึกข้อมูลที่เกี่ยวข้อง","attachments":"เอกสารแนบ","loading":"กำลังโหลด...","syncing":"ซิงค์ ...","errorData":"ข้อผิดพลาดเกี่ยวกับข้อมูล","errorLayer":"ข้อผิดพลาดเกี่ยวกับชั้นข้อมูล","errorUpdateFailed":"การอัพเดทล้มเหลว","errorDomainType":"ประเภทโดเมนไม่ได้รับการสนับสนุน","show":"แสดง","hide":"ซ่อน","menu":"เมนู","options":"ตัวเลือก","allColums":"คอลัมน์ทั้งหมด","sortAsc":"จัดเรียงจากน้อยไปมาก","sortDesc":"จัดเรียงจากมากไปน้อย","toggleColumns":"แสดง/ซ่อนคอลัมน์","clearSelection":"ล้างการเลือก","centerOnSelection":"กึ่งกลางของบริเวณที่เลือก","showSelected":"แสดงแถวข้อมูลที่เลือก","filter":"ตัวกรอง","addField":"เพิ่มฟิลด์","refreshData":"รีเฟรชข้อมูล","date":"วันที่","number":"จำนวน","string":"ตัวหนังสือ"}