{"widgetLabel":"Imprimir","title":"Título","fileName":"Nome do arquivo","titlePlaceHolder":"Título do arquivo","fileNamePlaceHolder":"Nome do arquivo","formatDefaultOption":"Selecionar formato","fileFormatTitle":"Formato do arquivo","layoutTitle":"Configuração da página","layoutDefaultOption":"Selecionar configuração da página","scale":"Configurar escala","scaleLabel":"escala","reset":"redefinir","author":"Autor","copyright":"Direitos autorais","legend":"Incluir legenda","lock":"bloquear","swap":"trocar","panelToggle":"Alternar painel","advancedOptions":"Opções avançadas","width":"Largura","height":"Altura","dpi":"DPI","attribution":"Incluir atribuição","layoutTab":"Layout","mapOnlyTab":"Mapa somente","untitled":"sem título","pending":"Exportando","ready":"Abrir este","linkReady":"Abrir em uma nova janela","errorMessage":"Selecione este para removê-lo.","sceneViewError":"A impressão não é suportada na Visualização de Cena.","serviceError":"Parece haver um erro.","export":"Exportar","exportDescription":"Exportar. Arquivos exportados aparecerão abaixo.","exportText":"Arquivos exportados","selectTemplate":"Selecionar modelo","selectTemplateDescription":"Utilizar um modelo aplicará seus valores","exportHint":"Seus arquivos exportados aparecerão aqui.","a3-landscape":"Paisagem A3","a3-portrait":"Retrato A3","a4-landscape":"Paisagem A4","a4-portrait":"Retrato A4","letter-ansi-a-landscape":"Paisagem Carta ANSI A","letter-ansi-a-portrait":"Retrato Carta ANSI A","tabloid-ansi-b-landscape":"Paisagem Tablóide ANSI B","tabloid-ansi-b-portrait":"Retrato Tablóide ANSI B"}