{"widgetLabel":"Editor","multipleFeaturesTemplate":"Diverses entitats ({total})","untitledFeatureTemplate":"Entitat sense títol {id}","editFeatures":"Edita entitats","editFeature":"Edita l'entitat","addFeature":"Afegeix una entitat","featureAttachments":"Fitxers adjunts d'entitats","attachmentsButtonLabel":"Fitxers adjunts","attachments":"Fitxers adjunts","addAttachment":"Afegeix un fitxer adjunt","editAttachment":"Administra el fitxer adjunt","selectTemplate":"Seleccioneu el tipus d'entitat","selectFeatureToEdit":"Seleccioneu una entitat per editar-la.","selectFeature":"Seleccioneu una entitat","placeFeature":"Col·loca l'entitat","placeFeatureOnMap":"Col·loca l'entitat al mapa.","add":"Afegeix","discardEdits":"Descarta les edicions","discardFeature":"Descarta l'entitat","edit":"Edita","keepAttachment":"Conserva el fitxer adjunt","keepFeature":"Mantén l'entitat","continueAdding":"Continua amb l'addició","continueEditing":"Continua amb l'edició","editing":"Edició","warning":"Avís","retry":"Torna-ho a provar","ignore":"Ignora","deleteWarningTitle":"Voleu suprimir aquesta entitat?","deleteAttachmentWarningTitle":"Voleu suprimir el fitxer adjunt?","deleteWarningMessage":"Aquesta entitat s'eliminarà permanentment.","deleteAttachmentWarningMessage":"Aquest fitxer adjunt s'eliminarà permanentment.","cancelEditTitle":"Voleu descartar les edicions?","cancelAddTitle":"Voleu descartar l'entitat?","cancelAddWarningMessage":"Aquesta entitat es perdrà.","cancelEditWarningMessage":"Les actualitzacions d'aquesta entitat es perdran.","cancelRequestTitle":"Voleu cancel·lar el flux de treball?","cancelRequestWarningMessage":"S'ha realitzat una sol·licitud per cancel·lar aquest flux de treball.","errorWarningTitle":"S'ha produït algun problema","errorWarningMessageTemplate":"Els canvis no s'han pogut desar: {errorMessage}","clickToFinishTemplate":"Feu clic a {button} per finalitzar.","tips":{"clickToStart":"Feu clic al mapa per començar a dibuixar.","clickToContinue":"Feu clic al mapa per continuar dibuixant.","clickToAddPoint":"Feu clic al mapa per afegir-hi un punt.","clickToContinueThenDoubleClickToEnd":"Feu clic al mapa per continuar dibuixant i, a continuació, feu-hi doble clic per acabar.","clickToAddFeature":"Feu clic al mapa per afegir-hi una entitat."}}