{"widgetLabel":"Conversión de coordenadas","abbreviatedDirections":{"north":"N","south":"S","east":"E","west":"O"},"addConversion":"Agregar conversión","captureMode":"Modo de captura","changeCoordinateDisplay":"Cambiar visualización de coordenadas","convert":"Convertir","conversionOutputSuffix":"salida de conversión","copySuccessMessage":"Coordenadas copiadas al portapapeles","defaultPattern":"Restablecer al valor predeterminado","goTo":"Ir a una ubicación","inputCoordTitle":"Coordenada de entrada","invalidCoordinate":"Coordenada no válida","liveMode":"Modo en directo","locationOffBasemap":"Coordenada de entrada fuera de la extensión del mapa base","noBasemap":"No hay ningún mapa base.","noLocation":"No hay ninguna posición","removeConversion":"Eliminar conversión","selectFormat":"Seleccionar formato","settingsTitle":"Configuración de formato"}