{"widgetLabel":"Скетч","move":"Перемістити","pan":"Переміщення","reset":"Скинути","reshape":"Змінити форму","rotate":"Повернути","scale":"Масштаб","transform":"Перетворити","undo":"Відмінити","redo":"Повторити","drawPoint":"Намалювати точку","drawPolygon":"Намалювати полігон","drawPolyline":"Намалювати полілінію","drawMultipoint":"Намалювати мультиточковий об'єкт","drawCircle":"Намалювати коло","drawRectangle":"Намалювати прямокутник","clearDrawing":"Очистити малюнок","completeDrawing":"Завершити малювання","pauseDrawing":"Призупинити малювання","resumeDrawing":"Відновити малювання","updateDrawing":"Оновити малюнок","addPointTooltip":"Клацніть, щоб додати точку","removePointTooltip":"Клацніть, щоб видалити цю точку","completePolygonTooltip":"Клацніть цю точку, щоб завершити","startDrawingTooltip":"Клацніть, щоб почати малювання","continueDrawingTooltip":"Клацніть, щоб продовжити малювання","completeDrawingTooltip":"Двічі клацніть, щоб завершити","addMultipointTooltip":"Клацніть, щоб почати додавання точок","finishMultipointTooltip":"Двічі клацніть, щоб завершити","addFreehandTooltip":"Натисніть і утримуйте, щоб почати, і відпустіть, щоб завершити","addShapeTooltip":"Клацніть, щоб додати форму, або натисніть і утримуйте, щоб почати, і відпустіть, щоб завершити","featureCount":"{count} Об’єкт","featuresCount":"{count} Об’єкти","vertexCount":"{count} Вершина","verticesCount":"{count} Вершини","deleteFeature":"Видалити об'єкт","deleteVertex":"Видалити вершину","duplicate":"Дублювати","selectCircle":"Вибрати за колом","selectFeature":"Вибрати об’єкт","selectFeatures":"Вибрати об’єкти","selectLasso":"Вибрати за лассо","selectLine":"Вибрати за лінією","selectMarquee":"Вибрати за рухомим рядком","selectPolygon":"Вибрати за полігоном","selectRectangle":"Вибрати за прямокутником","clearSelection":"Очистити вибір"}