{"about":"O aplikaci","add":"Přidat","all":"Všechny","apply":"Použít","auth":{"logOut":"Odhlásit","signIn":"Přihlásit"},"back":"Zpět","cancel":"Storno","change":"Změnit","clear":"Zrušit","close":"Zavřít","collapse":"Sbalit","configure":"Konfigurovat","control":{"pause":"Pozastavit","play":"Přehrát","resume":"Obnovit","stop":"Zastavit"},"copy":"Kopírovat","create":"Vytvořit","cut":"Vyjmout","delete":"Smazat","details":"Podrobnosti","done":"Hotovo","dragHandleTitle":"přetáhnout/uspořádat","dragHandleLabel":"Po kliknutí na tlačítko Uspořádat můžete pomocí šipek na klávesnici nebo pomocí přetažení jednotlivých položek myší změnit pořadí položek v seznamu. Pokud už jste s uspořádáváním vašeho seznamu skončili, stiskněte klávesu escape.","edit":"Editovat","errorMessage":"Chyba","esri":"Esri","exit":"Konec","expand":"Rozbalit","fieldsSummary":"Seznam atributů a hodnot","find":"Najít","form":{"no":"Ne","ok":"OK","password":"Heslo","submit":"Odeslat","username":"Uživatelské jméno","yes":"Ano"},"help":"Nápověda","home":"Domů","info":"Informace","information":"Informace","layer":"Vrstva","loading":"Načítání","maximize":"Maximalizovat","menu":"Nabídka","more":"Více","none":"Žádný","open":"Otevřít","pagination":{"first":"První","last":"Poslední","next":"Další","page":"Stránka","pageText":"{index} z {total}","previous":"Předchozí"},"paste":"Vložit","preview":"Náhled","print":"Tisk","publish":"Publikovat","redo":"Znovu","refresh":"Obnovit","remove":"Odebrat","rename":"Přejmenovat","reset":"Obnovit","restore":"Obnovit","save":"Uložit","search":"Hledat","searching":"Vyhledávání","select":"Vybrat","settings":"Nastavení","sort":"Seřadit","share":"Sdílet","title":"Nadpis","untitled":"Bez názvu","unnamed":"Beze jména","update":"Aktualizovat","upload":"Nahrát","undo":"Vrátit","view":"Zobrazit","visibility":{"hide":"Skrýt","show":"Zobrazit","toggle":"Přepnout"},"warning":"Varování"}