{"measures":{"length":"Độ dài","area":"Khu vực","volume":"Ổ đĩa","angle":"Góc"},"systems":{"metric":"Hệ mét","imperial":"Hệ đo lường Anh"},"units":{"millimeters":{"singular":"milimét","singularCapitalized":"Milimét","plural":"milimét","pluralCapitalized":"Milimét","abbr":"mm"},"centimeters":{"singular":"xentimét","singularCapitalized":"Xentimét","plural":"xentimét","pluralCapitalized":"Centimét","abbr":"cm"},"decimeters":{"singular":"đềximét","singularCapitalized":"Đềximét","plural":"đề-xi-mét","pluralCapitalized":"Đềximét","abbr":"dm"},"meters":{"singular":"mét","singularCapitalized":"Mét","plural":"mét","pluralCapitalized":"Mét","abbr":"m"},"kilometers":{"singular":"Kilômét","singularCapitalized":"Kilômét","plural":"ki-lô-mét","pluralCapitalized":"Kilômét","abbr":"km"},"inches":{"singular":"inch","singularCapitalized":"Inch","plural":"inch","pluralCapitalized":"Inch","abbr":"trong"},"feet":{"singular":"foot","singularCapitalized":"Foot","plural":"feet","pluralCapitalized":"Bộ","abbr":"ft"},"yards":{"singular":"thước","singularCapitalized":"Thước","plural":"thước","pluralCapitalized":"Yard","abbr":"yd"},"miles":{"singular":"dặm","singularCapitalized":"Dặm","plural":"dặm","pluralCapitalized":"Dặm","abbr":"mi"},"nautical-miles":{"singular":"hải lý","singularCapitalized":"Hải lý","plural":"hải lý","pluralCapitalized":"Hải lý","abbr":"nm"},"us-feet":{"singular":"foot (Mỹ)","singularCapitalized":"Foot (Mỹ)","plural":"feet (Mỹ)","pluralCapitalized":"Feet (Hoa Kỳ)","abbr":"ft"},"square-millimeters":{"singular":"millimét vuông","singularCapitalized":"Millimét vuông","plural":"millimét vuông","pluralCapitalized":"Millimét vuông","abbr":"mm²"},"square-centimeters":{"singular":"xentimét vuông","singularCapitalized":"Xentimét vuông","plural":"xentimét vuông","pluralCapitalized":"Xentimét vuông","abbr":"cm²"},"square-decimeters":{"singular":"đềximét vuông","singularCapitalized":"Đềximét vuông","plural":"đềximét vuông","pluralCapitalized":"Đềximét vuông","abbr":"dm²"},"square-meters":{"singular":"mét vuông","singularCapitalized":"Mét vuông","plural":"mét vuông","pluralCapitalized":"Mét vuông","abbr":"m²"},"square-kilometers":{"singular":"kilômét vuông","singularCapitalized":"Kilômét vuông","plural":"kilômét vuông","pluralCapitalized":"Kilômét vuông","abbr":"km²"},"square-inches":{"singular":"inch vuông","singularCapitalized":"Inch vuông","plural":"Inch vuông","pluralCapitalized":"Inch vuông","abbr":"in²"},"square-feet":{"singular":"foot vuông","singularCapitalized":"Foot vuông","plural":"feet vuông","pluralCapitalized":"Feet vuông","abbr":"ft²"},"square-yards":{"singular":"thước vuông","singularCapitalized":"Thước vuông","plural":"thước vuông","pluralCapitalized":"Thước vuông","abbr":"yd²"},"square-miles":{"singular":"dặm vuông","singularCapitalized":"Dặm vuông","plural":"dặm vuông","pluralCapitalized":"Dặm vuông","abbr":"mi²"},"square-us-feet":{"singular":"foot vuông (Mỹ)","singularCapitalized":"Foot vuông (Mỹ)","plural":"feet vuông (Mỹ)","pluralCapitalized":"Feet vuông (Mỹ)","abbr":"ft²"},"acres":{"singular":"mẫu Anh","singularCapitalized":"Mẫu Anh","plural":"acre","pluralCapitalized":"Acre","abbr":"mẫu Anh"},"ares":{"singular":"are","singularCapitalized":"Are","plural":"are","pluralCapitalized":"Are","abbr":"a"},"hectares":{"singular":"hecta","singularCapitalized":"hecta","plural":"hecta","pluralCapitalized":"Hecta","abbr":"ha"},"liters":{"singular":"lít","singularCapitalized":"Lít","plural":"lít","pluralCapitalized":"Lít","abbr":"l"},"cubic-millimeters":{"singular":"millimét khối","singularCapitalized":"Millimét khối","plural":"millimét khối","pluralCapitalized":"Millimét khối","abbr":"mm³"},"cubic-centimeters":{"singular":"xentimét khối","singularCapitalized":"Xentimét khối","plural":"xentimét khối","pluralCapitalized":"Xentimét khối","abbr":"cm³"},"cubic-decimeters":{"singular":"đềximét khối","singularCapitalized":"Đềximét khối","plural":"đềximét khối","pluralCapitalized":"Đềximét khối","abbr":"dm³"},"cubic-meters":{"singular":"mét khối","singularCapitalized":"Mét khối","plural":"mét khối","pluralCapitalized":"Mét khối","abbr":"m³"},"cubic-kilometers":{"singular":"kilômét khối","singularCapitalized":"Kilômét khối","plural":"kilômét khối","pluralCapitalized":"Kilômét khối","abbr":"km³"},"cubic-inches":{"singular":"inch khối","singularCapitalized":"Inch khối","plural":"inch khối","pluralCapitalized":"Inch khối","abbr":"in³"},"cubic-feet":{"singular":"foot khối","singularCapitalized":"Foot khối","plural":"feet khối","pluralCapitalized":"Feet khối","abbr":"ft³"},"cubic-yards":{"singular":"thước khối","singularCapitalized":"Thước khối","plural":"thước khối","pluralCapitalized":"Thước khối","abbr":"yd³"},"cubic-miles":{"singular":"dặm khối","singularCapitalized":"Dặm khối","plural":"dặm khối","pluralCapitalized":"Dặm khối","abbr":"mi³"},"radians":{"singular":"radian","singularCapitalized":"Radian","plural":"radian","pluralCapitalized":"Radian","abbr":""},"degrees":{"singular":"độ","singularCapitalized":"Độ","plural":"độ","pluralCapitalized":"Độ","abbr":"°"},"bytes":{"B":"{fileSize} B","kB":"{fileSize} kB","MB":"{fileSize} MB","GB":"{fileSize} GB","TB":"{fileSize} TB"}}}