{"widgetLabel":"Wyszukaj","searchButtonTitle":"Wyszukaj","clearButtonTitle":"Wyczyść wyszukiwanie","placeholder":"Znajdź adres lub miejsce","searchIn":"Szukaj w","all":"Wszystkie","allPlaceholder":"Znajdź adres lub miejsce","emptyValue":"Wprowadź wyszukiwany termin","locateError":"Nie można wczytać bieżącej lokalizacji.","untitledResult":"Bez tytułu","untitledSource":"Źródło bez nazwy","noResults":"Brak wyników","noResultsFound":"Nie znaleziono wyników.","noResultsFoundForValue":"Nie znaleziono wyników dla {value}.","showMoreResults":"Pokaż więcej wyników","hideMoreResults":"Ukryj","searchResult":"Wynik wyszukiwania","moreResultsHeader":"Więcej wyników","useCurrentLocation":"Użyj bieżącej lokalizacji"}