{"operationalLayers":[{"id":"14bad687af8-layer1","listMode":"show","title":"varying size Icons","layers":[{"id":"14bad687bc4-layer4","listMode":"show","title":"AboveRight","url":"https://servicesdev1.arcgis.com/5uh3wwYLNzBuU0Eu/arcgis/rest/services/drivers11/FeatureServer/1","layerType":"ArcGISFeatureLayer","layerDefinition":{"minScale":0,"maxScale":0,"definitionExpression":"idInt < 11","elevationInfo":{"mode":"relativeToGround","offset":1},"drawingInfo":{"labelingInfo":[{"labelExpression":"[styleitemname]","labelExpressionInfo":{"expression":"$feature[\"styleitemname\"]"},"labelPlacement":"esriServerPointLabelPlacementAboveRight","symbol":{"type":"LabelSymbol3D","symbolLayers":[{"type":"Text","font":{"family":"Arial","style":"italic","weight":"bold"},"material":{"color":[0,0,0]},"size":8,"text":"default"}]}}],"renderer":{"type":"simple","visualVariables":[{"type":"sizeInfo","field":"idInt","axis":"height","maxDataValue":28,"maxSize":64,"minDataValue":1,"minSize":8},{"type":"colorInfo","field":"idInt","stops":[{"color":[255,0,0,255],"value":1},{"color":[0,0,255,255],"value":28}]}],"symbol":{"type":"PointSymbol3D","symbolLayers":[{"type":"Icon","material":{"color":[0,255,0]},"resource":{"primitive":"kite"},"size":24}]}}}},"showLabels":true},{"id":"14bad687c3b-layer5","listMode":"show","title":"BelowCenter","url":"https://servicesdev1.arcgis.com/5uh3wwYLNzBuU0Eu/arcgis/rest/services/drivers11/FeatureServer/1","layerType":"ArcGISFeatureLayer","layerDefinition":{"minScale":0,"maxScale":0,"definitionExpression":"idInt < 11","elevationInfo":{"mode":"relativeToGround","offset":100},"drawingInfo":{"labelingInfo":[{"labelExpression":"[styleitemname]","labelExpressionInfo":{"expression":"$feature[\"styleitemname\"]"},"labelPlacement":"esriServerPointLabelPlacementBelowCenter","symbol":{"type":"LabelSymbol3D","symbolLayers":[{"type":"Text","font":{"family":"Arial","style":"italic","weight":"bold"},"material":{"color":[0,0,0]},"size":8,"text":"default"}]}}],"renderer":{"type":"simple","visualVariables":[{"type":"sizeInfo","field":"idInt","axis":"height","maxDataValue":28,"maxSize":64,"minDataValue":1,"minSize":8},{"type":"colorInfo","field":"idInt","stops":[{"color":[255,0,0,255],"value":1},{"color":[0,0,255,255],"value":28}]}],"symbol":{"type":"PointSymbol3D","symbolLayers":[{"type":"Icon","material":{"color":[0,255,0]},"resource":{"primitive":"kite"},"size":24}]}}}},"showLabels":true},{"id":"14bad687c43-layer6","listMode":"show","title":"AboveCenter","url":"https://servicesdev1.arcgis.com/5uh3wwYLNzBuU0Eu/arcgis/rest/services/drivers11/FeatureServer/1","layerType":"ArcGISFeatureLayer","layerDefinition":{"minScale":0,"maxScale":0,"definitionExpression":"idInt < 11","elevationInfo":{"mode":"relativeToGround","offset":200},"drawingInfo":{"labelingInfo":[{"labelExpression":"[styleitemname]","labelExpressionInfo":{"expression":"$feature[\"styleitemname\"]"},"labelPlacement":"esriServerPointLabelPlacementAboveCenter","symbol":{"type":"LabelSymbol3D","symbolLayers":[{"type":"Text","font":{"family":"Arial","style":"italic","weight":"bold"},"material":{"color":[0,0,0]},"size":8,"text":"default"}]}}],"renderer":{"type":"simple","visualVariables":[{"type":"sizeInfo","field":"idInt","axis":"height","maxDataValue":28,"maxSize":64,"minDataValue":1,"minSize":8},{"type":"colorInfo","field":"idInt","stops":[{"color":[255,0,0,255],"value":1},{"color":[0,0,255,255],"value":28}]}],"symbol":{"type":"PointSymbol3D","symbolLayers":[{"type":"Icon","material":{"color":[0,255,0]},"resource":{"primitive":"kite"},"size":24}]}}}},"showLabels":true},{"id":"14bad687cd3-layer11","listMode":"show","title":"CenterLeft","url":"https://servicesdev1.arcgis.com/5uh3wwYLNzBuU0Eu/arcgis/rest/services/drivers11/FeatureServer/1","layerType":"ArcGISFeatureLayer","layerDefinition":{"minScale":0,"maxScale":0,"definitionExpression":"idInt < 11","elevationInfo":{"mode":"relativeToGround","offset":300},"drawingInfo":{"labelingInfo":[{"labelExpression":"[styleitemname]","labelExpressionInfo":{"expression":"$feature[\"styleitemname\"]"},"labelPlacement":"esriServerPointLabelPlacementCenterLeft","symbol":{"type":"LabelSymbol3D","symbolLayers":[{"type":"Text","font":{"family":"Arial","style":"italic","weight":"bold"},"material":{"color":[0,0,0]},"size":8,"text":"default"}]}}],"renderer":{"type":"simple","visualVariables":[{"type":"sizeInfo","field":"idInt","axis":"height","maxDataValue":28,"maxSize":64,"minDataValue":1,"minSize":8},{"type":"colorInfo","field":"idInt","stops":[{"color":[255,0,0,255],"value":1},{"color":[0,0,255,255],"value":28}]}],"symbol":{"type":"PointSymbol3D","symbolLayers":[{"type":"Icon","material":{"color":[0,255,0]},"resource":{"primitive":"kite"},"size":24}]}}}},"showLabels":true},{"id":"14bad687ccc-layer10","listMode":"show","title":"CenterCenter","url":"https://servicesdev1.arcgis.com/5uh3wwYLNzBuU0Eu/arcgis/rest/services/drivers11/FeatureServer/1","layerType":"ArcGISFeatureLayer","layerDefinition":{"minScale":0,"maxScale":0,"definitionExpression":"idInt < 11","elevationInfo":{"mode":"relativeToGround","offset":400},"drawingInfo":{"labelingInfo":[{"labelExpression":"[styleitemname]","labelExpressionInfo":{"expression":"$feature[\"styleitemname\"]"},"labelPlacement":"esriServerPointLabelPlacementCenterCenter","symbol":{"type":"LabelSymbol3D","symbolLayers":[{"type":"Text","font":{"family":"Arial","style":"italic","weight":"bold"},"material":{"color":[0,0,0]},"size":8,"text":"default"}]}}],"renderer":{"type":"simple","visualVariables":[{"type":"sizeInfo","field":"idInt","axis":"height","maxDataValue":28,"maxSize":64,"minDataValue":1,"minSize":8},{"type":"colorInfo","field":"idInt","stops":[{"color":[255,0,0,255],"value":1},{"color":[0,0,255,255],"value":28}]}],"symbol":{"type":"PointSymbol3D","symbolLayers":[{"type":"Icon","material":{"color":[0,255,0]},"resource":{"primitive":"kite"},"size":24}]}}}},"showLabels":true}],"layerType":"GroupLayer","visibilityMode":"independent"},{"id":"14bad687b19-layer2","listMode":"show","title":"varying height object","layers":[{"id":"14bad687cc6-layer9","listMode":"show","title":"AboveRight","url":"https://servicesdev1.arcgis.com/5uh3wwYLNzBuU0Eu/arcgis/rest/services/drivers11/FeatureServer/0","layerType":"ArcGISFeatureLayer","layerDefinition":{"minScale":0,"maxScale":0,"elevationInfo":{"mode":"relativeToGround","offset":1},"drawingInfo":{"labelingInfo":[{"labelExpression":"[styleitemname]","labelExpressionInfo":{"expression":"$feature[\"styleitemname\"]"},"labelPlacement":"esriServerPointLabelPlacementAboveRight","symbol":{"type":"LabelSymbol3D","symbolLayers":[{"type":"Text","font":{"family":"Arial","style":"italic","weight":"bold"},"material":{"color":[0,0,0]},"size":10,"text":"default"}]}}],"renderer":{"type":"simple","visualVariables":[{"type":"sizeInfo","field":"idInt","axis":"height","maxDataValue":10,"maxSize":55,"minDataValue":0,"minSize":8},{"type":"sizeInfo","axis":"widthAndDepth","minSize":16},{"type":"colorInfo","field":"idInt","stops":[{"color":[255,0,0,255],"value":0},{"color":[0,0,255,255],"value":10}]}],"symbol":{"type":"PointSymbol3D","symbolLayers":[{"type":"Object","material":{"color":[0,255,0]},"resource":{"primitive":"cylinder"},"width":15,"height":30}]}}}},"showLabels":true},{"id":"14bad687d29-layer12","listMode":"show","title":"BelowCenter","url":"https://servicesdev1.arcgis.com/5uh3wwYLNzBuU0Eu/arcgis/rest/services/drivers11/FeatureServer/0","layerType":"ArcGISFeatureLayer","layerDefinition":{"minScale":0,"maxScale":0,"elevationInfo":{"mode":"relativeToGround","offset":100},"drawingInfo":{"labelingInfo":[{"labelExpression":"[styleitemname]","labelExpressionInfo":{"expression":"$feature[\"styleitemname\"]"},"labelPlacement":"esriServerPointLabelPlacementBelowCenter","symbol":{"type":"LabelSymbol3D","symbolLayers":[{"type":"Text","font":{"family":"Arial","style":"italic","weight":"bold"},"material":{"color":[0,0,0]},"size":10,"text":"default"}]}}],"renderer":{"type":"simple","visualVariables":[{"type":"sizeInfo","field":"idInt","axis":"height","maxDataValue":10,"maxSize":55,"minDataValue":0,"minSize":8},{"type":"sizeInfo","axis":"widthAndDepth","minSize":16},{"type":"colorInfo","field":"idInt","stops":[{"color":[255,0,0,255],"value":0},{"color":[0,0,255,255],"value":10}]}],"symbol":{"type":"PointSymbol3D","symbolLayers":[{"type":"Object","material":{"color":[0,255,0]},"resource":{"primitive":"cylinder"},"width":15,"height":30}]}}}},"showLabels":true},{"id":"14bad687d34-layer13","listMode":"show","title":"AboveCenter","url":"https://servicesdev1.arcgis.com/5uh3wwYLNzBuU0Eu/arcgis/rest/services/drivers11/FeatureServer/0","layerType":"ArcGISFeatureLayer","layerDefinition":{"minScale":0,"maxScale":0,"elevationInfo":{"mode":"relativeToGround","offset":200},"drawingInfo":{"labelingInfo":[{"labelExpression":"[styleitemname]","labelExpressionInfo":{"expression":"$feature[\"styleitemname\"]"},"labelPlacement":"esriServerPointLabelPlacementAboveCenter","symbol":{"type":"LabelSymbol3D","symbolLayers":[{"type":"Text","font":{"family":"Arial","style":"italic","weight":"bold"},"material":{"color":[0,0,0]},"size":10,"text":"default"}]}}],"renderer":{"type":"simple","visualVariables":[{"type":"sizeInfo","field":"idInt","axis":"height","maxDataValue":10,"maxSize":55,"minDataValue":0,"minSize":8},{"type":"sizeInfo","axis":"widthAndDepth","minSize":16},{"type":"colorInfo","field":"idInt","stops":[{"color":[255,0,0,255],"value":0},{"color":[0,0,255,255],"value":10}]}],"symbol":{"type":"PointSymbol3D","symbolLayers":[{"type":"Object","material":{"color":[0,255,0]},"resource":{"primitive":"cylinder"},"width":15,"height":30}]}}}},"showLabels":true},{"id":"14bad687e49-layer14","listMode":"show","title":"CenterLeft","url":"https://servicesdev1.arcgis.com/5uh3wwYLNzBuU0Eu/arcgis/rest/services/drivers11/FeatureServer/0","layerType":"ArcGISFeatureLayer","layerDefinition":{"minScale":0,"maxScale":0,"elevationInfo":{"mode":"relativeToGround","offset":300},"drawingInfo":{"labelingInfo":[{"labelExpression":"[styleitemname]","labelExpressionInfo":{"expression":"$feature[\"styleitemname\"]"},"labelPlacement":"esriServerPointLabelPlacementCenterLeft","symbol":{"type":"LabelSymbol3D","symbolLayers":[{"type":"Text","font":{"family":"Arial","style":"italic","weight":"bold"},"material":{"color":[0,0,0]},"size":10,"text":"default"}]}}],"renderer":{"type":"simple","visualVariables":[{"type":"sizeInfo","field":"idInt","axis":"height","maxDataValue":10,"maxSize":55,"minDataValue":0,"minSize":8},{"type":"sizeInfo","axis":"widthAndDepth","minSize":16},{"type":"colorInfo","field":"idInt","stops":[{"color":[255,0,0,255],"value":0},{"color":[0,0,255,255],"value":10}]}],"symbol":{"type":"PointSymbol3D","symbolLayers":[{"type":"Object","material":{"color":[0,255,0]},"resource":{"primitive":"cylinder"},"width":15,"height":30}]}}}},"showLabels":true},{"id":"14bad687ee5-layer15","listMode":"show","title":"CenterCenter","url":"https://servicesdev1.arcgis.com/5uh3wwYLNzBuU0Eu/arcgis/rest/services/drivers11/FeatureServer/0","layerType":"ArcGISFeatureLayer","layerDefinition":{"minScale":0,"maxScale":0,"elevationInfo":{"mode":"relativeToGround","offset":400},"drawingInfo":{"labelingInfo":[{"labelExpression":"[styleitemname]","labelExpressionInfo":{"expression":"$feature[\"styleitemname\"]"},"labelPlacement":"esriServerPointLabelPlacementCenterCenter","symbol":{"type":"LabelSymbol3D","symbolLayers":[{"type":"Text","font":{"family":"Arial","style":"italic","weight":"bold"},"material":{"color":[0,0,0]},"size":10,"text":"default"}]}}],"renderer":{"type":"simple","visualVariables":[{"type":"sizeInfo","field":"idInt","axis":"height","maxDataValue":10,"maxSize":55,"minDataValue":0,"minSize":8},{"type":"sizeInfo","axis":"widthAndDepth","minSize":16},{"type":"colorInfo","field":"idInt","stops":[{"color":[255,0,0,255],"value":0},{"color":[0,0,255,255],"value":10}]}],"symbol":{"type":"PointSymbol3D","symbolLayers":[{"type":"Object","material":{"color":[0,255,0]},"resource":{"primitive":"cylinder"},"width":15,"height":30}]}}}},"showLabels":true}],"layerType":"GroupLayer","visibilityMode":"independent"},{"id":"14bad687b3a-layer3","listMode":"show","title":"varying radius object","visibility":false,"layers":[{"id":"14bad687f47-layer16","listMode":"show","title":"AboveRight","url":"https://servicesdev1.arcgis.com/5uh3wwYLNzBuU0Eu/arcgis/rest/services/drivers11/FeatureServer/0","layerType":"ArcGISFeatureLayer","layerDefinition":{"minScale":0,"maxScale":0,"elevationInfo":{"mode":"relativeToGround","offset":1},"drawingInfo":{"labelingInfo":[{"labelExpression":"[styleitemname]","labelExpressionInfo":{"expression":"$feature[\"styleitemname\"]"},"labelPlacement":"esriServerPointLabelPlacementAboveRight","symbol":{"type":"LabelSymbol3D","symbolLayers":[{"type":"Text","font":{"family":"Arial","style":"italic","weight":"bold"},"material":{"color":[0,0,0]},"size":10,"text":"default"}]}}],"renderer":{"type":"simple","visualVariables":[{"type":"sizeInfo","field":"idInt","axis":"widthAndDepth","maxDataValue":10,"maxSize":64,"minDataValue":0,"minSize":8},{"type":"sizeInfo","axis":"height","minSize":8},{"type":"colorInfo","field":"idInt","stops":[{"color":[255,0,0,255],"value":0},{"color":[0,0,255,255],"value":10}]}],"symbol":{"type":"PointSymbol3D","symbolLayers":[{"type":"Object","material":{"color":[0,255,0]},"resource":{"primitive":"cylinder"},"width":15,"height":30}]}}}},"showLabels":true},{"id":"14bad687fab-layer17","listMode":"show","title":"BelowCenter","url":"https://servicesdev1.arcgis.com/5uh3wwYLNzBuU0Eu/arcgis/rest/services/drivers11/FeatureServer/0","layerType":"ArcGISFeatureLayer","layerDefinition":{"minScale":0,"maxScale":0,"elevationInfo":{"mode":"relativeToGround","offset":100},"drawingInfo":{"labelingInfo":[{"labelExpression":"[styleitemname]","labelExpressionInfo":{"expression":"$feature[\"styleitemname\"]"},"labelPlacement":"esriServerPointLabelPlacementBelowCenter","symbol":{"type":"LabelSymbol3D","symbolLayers":[{"type":"Text","font":{"family":"Arial","style":"italic","weight":"bold"},"material":{"color":[0,0,0]},"size":10,"text":"default"}]}}],"renderer":{"type":"simple","visualVariables":[{"type":"sizeInfo","field":"idInt","axis":"widthAndDepth","maxDataValue":10,"maxSize":64,"minDataValue":0,"minSize":8},{"type":"sizeInfo","axis":"height","minSize":8},{"type":"colorInfo","field":"idInt","stops":[{"color":[255,0,0,255],"value":0},{"color":[0,0,255,255],"value":10}]}],"symbol":{"type":"PointSymbol3D","symbolLayers":[{"type":"Object","material":{"color":[0,255,0]},"resource":{"primitive":"cylinder"},"width":15,"height":30}]}}}},"showLabels":true},{"id":"14bad688076-layer18","listMode":"show","title":"AboveCenter","url":"https://servicesdev1.arcgis.com/5uh3wwYLNzBuU0Eu/arcgis/rest/services/drivers11/FeatureServer/0","layerType":"ArcGISFeatureLayer","layerDefinition":{"minScale":0,"maxScale":0,"elevationInfo":{"mode":"relativeToGround","offset":200},"drawingInfo":{"labelingInfo":[{"labelExpression":"[styleitemname]","labelExpressionInfo":{"expression":"$feature[\"styleitemname\"]"},"labelPlacement":"esriServerPointLabelPlacementAboveCenter","symbol":{"type":"LabelSymbol3D","symbolLayers":[{"type":"Text","font":{"family":"Arial","style":"italic","weight":"bold"},"material":{"color":[0,0,0]},"size":10,"text":"default"}]}}],"renderer":{"type":"simple","visualVariables":[{"type":"sizeInfo","field":"idInt","axis":"widthAndDepth","maxDataValue":10,"maxSize":64,"minDataValue":0,"minSize":8},{"type":"sizeInfo","axis":"height","minSize":8},{"type":"colorInfo","field":"idInt","stops":[{"color":[255,0,0,255],"value":0},{"color":[0,0,255,255],"value":10}]}],"symbol":{"type":"PointSymbol3D","symbolLayers":[{"type":"Object","material":{"color":[0,255,0]},"resource":{"primitive":"cylinder"},"width":15,"height":30}]}}}},"showLabels":true},{"id":"14bad68816d-layer20","listMode":"show","title":"CenterLeft","url":"https://servicesdev1.arcgis.com/5uh3wwYLNzBuU0Eu/arcgis/rest/services/drivers11/FeatureServer/0","layerType":"ArcGISFeatureLayer","layerDefinition":{"minScale":0,"maxScale":0,"elevationInfo":{"mode":"relativeToGround","offset":300},"drawingInfo":{"labelingInfo":[{"labelExpression":"[styleitemname]","labelExpressionInfo":{"expression":"$feature[\"styleitemname\"]"},"labelPlacement":"esriServerPointLabelPlacementCenterLeft","symbol":{"type":"LabelSymbol3D","symbolLayers":[{"type":"Text","font":{"family":"Arial","style":"italic","weight":"bold"},"material":{"color":[0,0,0]},"size":10,"text":"default"}]}}],"renderer":{"type":"simple","visualVariables":[{"type":"sizeInfo","field":"idInt","axis":"widthAndDepth","maxDataValue":10,"maxSize":64,"minDataValue":0,"minSize":8},{"type":"sizeInfo","axis":"height","minSize":8},{"type":"colorInfo","field":"idInt","stops":[{"color":[255,0,0,255],"value":0},{"color":[0,0,255,255],"value":10}]}],"symbol":{"type":"PointSymbol3D","symbolLayers":[{"type":"Object","material":{"color":[0,255,0]},"resource":{"primitive":"cylinder"},"width":15,"height":30}]}}}},"showLabels":true},{"id":"14bad6880f7-layer19","listMode":"show","title":"CenterCenter","url":"https://servicesdev1.arcgis.com/5uh3wwYLNzBuU0Eu/arcgis/rest/services/drivers11/FeatureServer/0","layerType":"ArcGISFeatureLayer","layerDefinition":{"minScale":0,"maxScale":0,"elevationInfo":{"mode":"relativeToGround","offset":400},"drawingInfo":{"labelingInfo":[{"labelExpression":"[styleitemname]","labelExpressionInfo":{"expression":"$feature[\"styleitemname\"]"},"labelPlacement":"esriServerPointLabelPlacementCenterCenter","symbol":{"type":"LabelSymbol3D","symbolLayers":[{"type":"Text","font":{"family":"Arial","style":"italic","weight":"bold"},"material":{"color":[0,0,0]},"size":10,"text":"default"}]}}],"renderer":{"type":"simple","visualVariables":[{"type":"sizeInfo","field":"idInt","axis":"widthAndDepth","maxDataValue":10,"maxSize":64,"minDataValue":0,"minSize":8},{"type":"sizeInfo","axis":"height","minSize":8},{"type":"colorInfo","field":"idInt","stops":[{"color":[255,0,0,255],"value":0},{"color":[0,0,255,255],"value":10}]}],"symbol":{"type":"PointSymbol3D","symbolLayers":[{"type":"Object","material":{"color":[0,255,0]},"resource":{"primitive":"cylinder"},"width":15,"height":30}]}}}},"showLabels":true}],"layerType":"GroupLayer","visibilityMode":"independent"}],"baseMap":{"baseMapLayers":[{"id":"14df2e1c6eb-layer-88","title":"World Topo Map","url":"https://services.arcgisonline.com/ArcGIS/rest/services/World_Topo_Map/MapServer","layerType":"ArcGISTiledMapServiceLayer"}],"id":"basemap","title":"Topographic","elevationLayers":[{"id":"globalElevation","listMode":"show","title":"Terrain3D","url":"https://elevation3d.arcgis.com/arcgis/rest/services/WorldElevation3D/Terrain3D/ImageServer","layerType":"ArcGISTiledElevationServiceLayer"}]},"ground":{"layers":[{"id":"globalElevation","listMode":"show","title":"Terrain3D","url":"https://elevation3d.arcgis.com/arcgis/rest/services/WorldElevation3D/Terrain3D/ImageServer","layerType":"ArcGISTiledElevationServiceLayer"}],"transparency":0},"version":"1.18","authoringApp":"ArcGIS API for JavaScript","authoringAppVersion":"4.14","initialState":{"environment":{"lighting":{"datetime":1426419727000,"displayUTCOffset":0},"atmosphereEnabled":true,"starsEnabled":true},"viewpoint":{"camera":{"position":{"spatialReference":{"latestWkid":3857,"wkid":102100},"x":497912.81025158975,"y":6788422.3225841075,"z":388.9023453546688},"heading":0.19626301908238789,"tilt":65.28429740663603}}},"spatialReference":{"latestWkid":3857,"wkid":102100},"viewingMode":"global"}